acribis_scores/__init__.py
acribis_scores/abc_af_bleeding.py
acribis_scores/abc_af_death.py
acribis_scores/abc_af_stroke.py
acribis_scores/barcelona_hf_v3.py
acribis_scores/batch_processing.py
acribis_scores/chads_vasc.py
acribis_scores/charge_af.py
acribis_scores/has_bled.py
acribis_scores/maggic.py
acribis_scores/smart.py
acribis_scores/smart_reach.py
acribis_scores/value_range.py
acribis_scores/resources/__init__.py
acribis_scores/resources/barcelona_hf_v3_death_coefficients.csv
acribis_scores/resources/barcelona_hf_v3_hosp_coefficients.csv
acribis_scores/resources/barcelona_hf_v3_hosp_death_coefficients.csv
acribis_scores/resources/barcelona_hf_v3_life_expectancy_coefficients.csv
acribis_scores/resources/life_expectancy_limits.csv
acribis_scores-0.4.0.dist-info/licenses/LICENSE
acribis_scores-0.4.0.dist-info/METADATA
acribis_scores-0.4.0.dist-info/WHEEL
acribis_scores-0.4.0.dist-info/top_level.txt
acribis_scores-0.4.0.dist-info/RECORD
