Metadata-Version: 2.4
Name: acribis_scores
Version: 0.4.0
Summary: Implementation of several cardiovascular risk scores
Author-email: Philipp Goos <philipp.goos@med.uni-heidelberg.de>, Sanketa Hegde <sanketa.hegde@uni-heidelberg.de>, Merten Prüser <merten.prueser@med.uni-heidelberg.de>, Erenik Krasniqi <erenik.krasniqi@med.uni-heidelberg.de>
License-Expression: GPL-3.0-only
Project-URL: Homepage, https://github.com/IMI-HD/acribis_scores_python
Project-URL: Issues, https://github.com/IMI-HD/acribis_scores_python/issues
Keywords: cvd risk,risk score,cha2ds2-vasc,has-bled,charge-af,abc-af,bcn bio-hf,smart,smart-reach,maggic
Classifier: Programming Language :: Python :: 3
Classifier: Operating System :: OS Independent
Classifier: Topic :: Scientific/Engineering :: Medical Science Apps.
Requires-Python: >=3.11
License-File: LICENSE
Requires-Dist: pandas>=2.2.3
Provides-Extra: test
Requires-Dist: selenium>=4.38.0; extra == "test"
Requires-Dist: openpyxl>=3.1.5; platform_system == "Windows" and extra == "test"
Requires-Dist: pywin32>=308; platform_system == "Windows" and extra == "test"
Dynamic: license-file
